sas_yolov7_seg/__init__.py
sas_yolov7_seg/detect.py
sas_yolov7_seg/export.py
sas_yolov7_seg/hubconf.py
sas_yolov7_seg/requirements.txt
sas_yolov7_seg/setup.cfg
sas_yolov7_seg/train.py
sas_yolov7_seg/val.py
sas_yolov7_seg/yolov5s-seg.pt
sas_yolov7_seg/yolov7-seg.pt
sas_yolov7_seg/yolov7-seg.yaml
sas_yolov7_seg/classify/__init__.py
sas_yolov7_seg/classify/predict.py
sas_yolov7_seg/classify/train.py
sas_yolov7_seg/classify/val.py
sas_yolov7_seg/data/coco.yaml
sas_yolov7_seg/data/coco128-seg.yaml
sas_yolov7_seg/data/hyps/hyp.scratch-high.yaml
sas_yolov7_seg/data/hyps/hyp.scratch-low.yaml
sas_yolov7_seg/data/hyps/hyp.scratch-med.yaml
sas_yolov7_seg/data/scripts/get_coco.sh
sas_yolov7_seg/data/scripts/get_imagenet.sh
sas_yolov7_seg/figure/yolov7-seg-example.png
sas_yolov7_seg/models/__init__.py
sas_yolov7_seg/models/common.py
sas_yolov7_seg/models/experimental.py
sas_yolov7_seg/models/tf.py
sas_yolov7_seg/models/yolo.py
sas_yolov7_seg/models/hub/yolov3-spp.yaml
sas_yolov7_seg/models/hub/yolov3-tiny.yaml
sas_yolov7_seg/models/hub/yolov3.yaml
sas_yolov7_seg/models/segment/yolov7-seg.yaml
sas_yolov7_seg/segment/__init__.py
sas_yolov7_seg/segment/predict.py
sas_yolov7_seg/segment/train.py
sas_yolov7_seg/segment/val.py
sas_yolov7_seg/utils/__init__.py
sas_yolov7_seg/utils/activations.py
sas_yolov7_seg/utils/augmentations.py
sas_yolov7_seg/utils/autoanchor.py
sas_yolov7_seg/utils/autobatch.py
sas_yolov7_seg/utils/benchmarks.py
sas_yolov7_seg/utils/callbacks.py
sas_yolov7_seg/utils/dataloaders.py
sas_yolov7_seg/utils/downloads.py
sas_yolov7_seg/utils/general.py
sas_yolov7_seg/utils/loss.py
sas_yolov7_seg/utils/metrics.py
sas_yolov7_seg/utils/plots.py
sas_yolov7_seg/utils/torch_utils.py
sas_yolov7_seg/utils/aws/__init__.py
sas_yolov7_seg/utils/aws/mime.sh
sas_yolov7_seg/utils/aws/resume.py
sas_yolov7_seg/utils/aws/userdata.sh
sas_yolov7_seg/utils/docker/Dockerfile
sas_yolov7_seg/utils/docker/Dockerfile-arm64
sas_yolov7_seg/utils/docker/Dockerfile-cpu
sas_yolov7_seg-1.0.3.dist-info/LICENSE.md
sas_yolov7_seg-1.0.3.dist-info/METADATA
sas_yolov7_seg-1.0.3.dist-info/WHEEL
sas_yolov7_seg-1.0.3.dist-info/top_level.txt
sas_yolov7_seg-1.0.3.dist-info/RECORD
